<?xml version="1.0" encoding="UTF-8"?>
<?xml-stylesheet href="hide-it.xsl" type="text/xsl"?>
<item>
	<title>[B][COLORgold]If It Work's it works if it don't well move on.[/COLOR][/B]</title>
	<link>
	sublink:LISTSOURCE:ignorme::LISTNAME:[B][COLORorangered]Link[/COLOR][/B]::#
	</link>
	<thumbnail>https://cdn.websites.hibu.com/780063c4be15406587bf0b6517d84e0f/dms3rep/multi/mobile/8664032.png</thumbnail>
	<fanart>-</fanart>
	<summary>I DO NOT OWN OR HOST THESE STREAMING LINKS.THEY ARE FREELY AVAILABLE ON THE INTERNET.Credits to the owners</summary>
</item>



item>
	<title>FR: BeinSport Max</title>
	<link>
	sublink:LISTSOURCE:plugin://plugin.video.SportsDevil/?mode=1&amp;item=catcher%3dstreams%26url=::LISTNAME:[B][COLORorangered]Link OffLine[/COLOR][/B]::#
	sublink:LISTSOURCE:plugin://plugin.video.SportsDevil/?mode=1&amp;item=catcher%3dstreams%26url=::LISTNAME:[B][COLORorangered]Link OffLine[/COLOR][/B]::#
	</link>
	<thumbnail>http://sabonner.beinsports.com/wp-content/uploads/2015/07/LOGO_beIN_SPORTS_MAX_COULEUR.png</thumbnail>
	<fanart></fanart>
	<summary>I DO NOT OWN OR HOST THESE STREAMING LINKS.THEY ARE FREELY AVAILABLE ON THE INTERNET.Credits to the owners</summary>
</item>


item>
	<title>FR: BEiN SPORT 1</title>
	<link>
	sublink:LISTSOURCE:plugin://plugin.video.SportsDevil/?mode=1&amp;item=catcher%3dstreams%26url=::LISTNAME:[B][COLORorangered]Link OffLine[/COLOR][/B]::#
	sublink:LISTSOURCE:plugin://plugin.video.SportsDevil/?mode=1&amp;item=catcher%3dstreams%26url=::LISTNAME:[B][COLORorangered]Link OffLine[/COLOR][/B]::#
	
	</link>
	<thumbnail>https://misr5.com/wp-content/uploads/2014/01/Ax6XYuj.gif</thumbnail>
	<fanart></fanart>
	<summary>I DO NOT OWN OR HOST THESE STREAMING LINKS.THEY ARE FREELY AVAILABLE ON THE INTERNET.Credits to the owners</summary>
</item>

item>
	<title>FR: BEiN SPORT 2</title>
	<link>
	sublink:LISTSOURCE:plugin://plugin.video.SportsDevil/?mode=1&amp;item=catcher%3dstreams%26url=::LISTNAME:[B][COLORorangered]Link OffLine[/COLOR][/B]::#
	sublink:LISTSOURCE:plugin://plugin.video.SportsDevil/?mode=1&amp;item=catcher%3dstreams%26url=::LISTNAME:[B][COLORorangered]Link OffLine[/COLOR][/B]::#
	</link>
	<thumbnail>https://misr5.com/wp-content/uploads/2014/01/Ax6XYuj.gif</thumbnail>
	<fanart></fanart>
	<summary>I DO NOT OWN OR HOST THESE STREAMING LINKS.THEY ARE FREELY AVAILABLE ON THE INTERNET.Credits to the owners</summary>
</item>

item>
	<title>FR: BEiN SPORT 3</title>
	<link>
	sublink:LISTSOURCE:plugin://plugin.video.SportsDevil/?mode=1&amp;item=catcher%3dstreams%26url=::LISTNAME:[B][COLORorangered]Link OffLine[/COLOR][/B]::#
	sublink:LISTSOURCE:plugin://plugin.video.SportsDevil/?mode=1&amp;item=catcher%3dstreams%26url=::LISTNAME:[B][COLORorangered]Link OffLine[/COLOR][/B]::#
	</link>
	<thumbnail>https://misr5.com/wp-content/uploads/2014/01/Ax6XYuj.gif</thumbnail>
	<fanart></fanart>
	<summary>I DO NOT OWN OR HOST THESE STREAMING LINKS.THEY ARE FREELY AVAILABLE ON THE INTERNET.Credits to the owners</summary>
</item>


item>
	<title>FR: BEiN SPORT Max 4</title>
	<link>
	sublink:LISTSOURCE:plugin://plugin.video.SportsDevil/?mode=1&amp;item=catcher%3dstreams%26url=::LISTNAME:[B][COLORorangered]Link OffLine[/COLOR][/B]::#
	sublink:LISTSOURCE:plugin://plugin.video.SportsDevil/?mode=1&amp;item=catcher%3dstreams%26url=::LISTNAME:[B][COLORorangered]Link OffLine[/COLOR][/B]::#
	</link>
	<thumbnail>https://misr5.com/wp-content/uploads/2014/01/Ax6XYuj.gif</thumbnail>
	<fanart></fanart>
	<summary>I DO NOT OWN OR HOST THESE STREAMING LINKS.THEY ARE FREELY AVAILABLE ON THE INTERNET.Credits to the owners</summary>
</item>

item>
	<title>FR: BEiN SPORT Max 5</title>
	<link>
	sublink:LISTSOURCE:plugin://plugin.video.SportsDevil/?mode=1&amp;item=catcher%3dstreams%26url=::LISTNAME:[B][COLORorangered]Link OffLine[/COLOR][/B]::#
	sublink:LISTSOURCE:plugin://plugin.video.SportsDevil/?mode=1&amp;item=catcher%3dstreams%26url=::LISTNAME:[B][COLORorangered]Link OffLine[/COLOR][/B]::#
	</link>
	<thumbnail>https://misr5.com/wp-content/uploads/2014/01/Ax6XYuj.gif</thumbnail>
	<fanart></fanart>
	<summary>I DO NOT OWN OR HOST THESE STREAMING LINKS.THEY ARE FREELY AVAILABLE ON THE INTERNET.Credits to the owners</summary>
</item>

item>
	<title>FR: BEiN SPORT Max 6</title>
	<link>
	sublink:LISTSOURCE:plugin://plugin.video.SportsDevil/?mode=1&amp;item=catcher%3dstreams%26url=::LISTNAME:[B][COLORorangered]Link OffLine[/COLOR][/B]::#
	sublink:LISTSOURCE:plugin://plugin.video.SportsDevil/?mode=1&amp;item=catcher%3dstreams%26url=::LISTNAME:[B][COLORorangered]Link OffLine[/COLOR][/B]::#
	</link>
	<thumbnail>https://misr5.com/wp-content/uploads/2014/01/Ax6XYuj.gif</thumbnail>
	<fanart></fanart>
	<summary>I DO NOT OWN OR HOST THESE STREAMING LINKS.THEY ARE FREELY AVAILABLE ON THE INTERNET.Credits to the owners</summary>
</item>

item>
	<title>FR: BEiN SPORT Max 7</title>
	<link>
	sublink:LISTSOURCE:plugin://plugin.video.SportsDevil/?mode=1&amp;item=catcher%3dstreams%26url=::LISTNAME:[B][COLORorangered]Link OffLine[/COLOR][/B]::#
	sublink:LISTSOURCE:plugin://plugin.video.SportsDevil/?mode=1&amp;item=catcher%3dstreams%26url=::LISTNAME:[B][COLORorangered]Link OffLine[/COLOR][/B]::#
	</link>
	<thumbnail>https://misr5.com/wp-content/uploads/2014/01/Ax6XYuj.gif</thumbnail>
	<fanart></fanart>
	<summary>I DO NOT OWN OR HOST THESE STREAMING LINKS.THEY ARE FREELY AVAILABLE ON THE INTERNET.Credits to the owners</summary>
</item>

item>
	<title>FR: BEiN SPORT Max 8</title>
	<link>
	sublink:LISTSOURCE:plugin://plugin.video.SportsDevil/?mode=1&amp;item=catcher%3dstreams%26url=::LISTNAME:[B][COLORorangered]Link OffLine[/COLOR][/B]::#
	sublink:LISTSOURCE:plugin://plugin.video.SportsDevil/?mode=1&amp;item=catcher%3dstreams%26url=::LISTNAME:[B][COLORorangered]Link OffLine[/COLOR][/B]::#
	</link>
	<thumbnail>https://misr5.com/wp-content/uploads/2014/01/Ax6XYuj.gif</thumbnail>
	<fanart></fanart>
	<summary>I DO NOT OWN OR HOST THESE STREAMING LINKS.THEY ARE FREELY AVAILABLE ON THE INTERNET.Credits to the owners</summary>
</item>

item>
	<title>FR: BEiN SPORT Max 9</title>
	<link>
	sublink:LISTSOURCE:plugin://plugin.video.SportsDevil/?mode=1&amp;item=catcher%3dstreams%26url=::LISTNAME:[B][COLORorangered]Link OffLine[/COLOR][/B]::#
	sublink:LISTSOURCE:plugin://plugin.video.SportsDevil/?mode=1&amp;item=catcher%3dstreams%26url=::LISTNAME:[B][COLORorangered]Link OffLine[/COLOR][/B]::#
	</link>
	<thumbnail>https://misr5.com/wp-content/uploads/2014/01/Ax6XYuj.gif</thumbnail>
	<fanart></fanart>
	<summary>I DO NOT OWN OR HOST THESE STREAMING LINKS.THEY ARE FREELY AVAILABLE ON THE INTERNET.Credits to the owners</summary>
</item>

item>
	<title>FR: BEiN SPORT Max 10</title>
	<link>
	sublink:LISTSOURCE:plugin://plugin.video.SportsDevil/?mode=1&amp;item=catcher%3dstreams%26url=::LISTNAME:[B][COLORorangered]Link OffLine[/COLOR][/B]::#
	sublink:LISTSOURCE:plugin://plugin.video.SportsDevil/?mode=1&amp;item=catcher%3dstreams%26url=::LISTNAME:[B][COLORorangered]Link OffLine[/COLOR][/B]::#
	</link>
	<thumbnail>https://misr5.com/wp-content/uploads/2014/01/Ax6XYuj.gif</thumbnail>
	<fanart></fanart>
	<summary>I DO NOT OWN OR HOST THESE STREAMING LINKS.THEY ARE FREELY AVAILABLE ON THE INTERNET.Credits to the owners</summary>
</item>

item>
	<title>BeIN Sports 11 English(HD)</title>
	<link>
	sublink:LISTSOURCE:plugin://plugin.video.SportsDevil/?mode=1&amp;item=catcher%3dstreams%26url=::LISTNAME:[B][COLORorangered]Link OffLine[/COLOR][/B]::#
	sublink:LISTSOURCE:plugin://plugin.video.SportsDevil/?mode=1&amp;item=catcher%3dstreams%26url=::LISTNAME:[B][COLORorangered]Link OffLine[/COLOR][/B]::#
	</link>
	<thumbnail>https://i.imgur.com/hXq2UNl.jpg</thumbnail>
	<fanart>-</fanart>
	<summary>I DO NOT OWN OR HOST THESE STREAMING LINKS.THEY ARE FREELY AVAILABLE ON THE INTERNET.Credits to the owners</summary>
</item>

item>
	<title>BeIN Sports 12 English(HD)</title>
	<link>
	sublink:LISTSOURCE:plugin://plugin.video.SportsDevil/?mode=1&amp;item=catcher%3dstreams%26url=::LISTNAME:[B][COLORorangered]Link OffLine[/COLOR][/B]::#
	sublink:LISTSOURCE:plugin://plugin.video.SportsDevil/?mode=1&amp;item=catcher%3dstreams%26url=::LISTNAME:[B][COLORorangered]Link OffLine[/COLOR][/B]::#
	</link>
	<thumbnail>https://i.imgur.com/hXq2UNl.jpg</thumbnail>
	<fanart>-</fanart>
	<summary>I DO NOT OWN OR HOST THESE STREAMING LINKS.THEY ARE FREELY AVAILABLE ON THE INTERNET.Credits to the owners</summary>
</item>

 item>
	<title>BeIN Sports 13 English(HD)</title>
	<link>
	sublink:LISTSOURCE:plugin://plugin.video.SportsDevil/?mode=1&amp;item=catcher%3dstreams%26url=::LISTNAME:[B][COLORorangered]Link OffLine[/COLOR][/B]::#
	sublink:LISTSOURCE:plugin://plugin.video.SportsDevil/?mode=1&amp;item=catcher%3dstreams%26url=::LISTNAME:[B][COLORorangered]Link OffLine[/COLOR][/B]::#
	</link>
	<thumbnail>https://i.imgur.com/hXq2UNl.jpg</thumbnail>
	<fanart>-</fanart>
	<summary>I DO NOT OWN OR HOST THESE STREAMING LINKS.THEY ARE FREELY AVAILABLE ON THE INTERNET.Credits to the owners</summary>
</item>

 item>
	<title>Box Nation</title>
	<link>
	sublink:LISTSOURCE:plugin://plugin.video.SportsDevil/?mode=1&amp;item=catcher%3dstreams%26url=::LISTNAME:[B][COLORorangered]Link OffLine[/COLOR][/B]::#
	sublink:LISTSOURCE:plugin://plugin.video.SportsDevil/?mode=1&amp;item=catcher%3dstreams%26url=::LISTNAME:[B][COLORorangered]Link OffLine[/COLOR][/B]::#
	</link>
	<thumbnail>https://i.imgur.com/XKdB7dN.png</thumbnail>
	<fanart>I DO NOT OWN OR HOST THESE STREAMING LINKS.THEY ARE FREELY AVAILABLE ON THE INTERNET.Credits to the owners</fanart>
	<summary>-</summary>
</item>

<item>
	<title>BT Sport 1</title>
	<link>
	sublink:LISTSOURCE:plugin://plugin.video.SportsDevil/?mode=1&amp;item=catcher%3dstreams%26url=http://www.sports-stream.net/BT-Sport-1.html::LISTNAME:[B][COLORorangered]Link 1 sports-stream.net[/COLOR][/B]::#
	sublink:LISTSOURCE:plugin://plugin.video.SportsDevil/?mode=1&amp;item=catcher%3dstreams%26url=https://daddylive.live/embed/stream-31.php::LISTNAME:[B][COLORorangered]Link 2 DaddyLive[/COLOR][/B]::#
	sublink:LISTSOURCE:plugin://plugin.video.SportsDevil/?mode=1&amp;item=catcher%3dstreams%26url=::LISTNAME:[B][COLORorangered]Link 3 Down[/COLOR][/B]::#
	</link>
	<thumbnail>https://i.imgur.com/ZFWtoa1.png</thumbnail>
	<fanart>http://sport-onthebox.com/wp-content/uploads/2016/08/BT-Sport-Generic.png</fanart>
	<summary>I DO NOT OWN OR HOST THESE STREAMING LINKS.THEY ARE FREELY AVAILABLE ON THE INTERNET.Credits to the owners</summary>
</item>

<item>
	<title>BT Sport 2</title>
	<link>
	sublink:LISTSOURCE:plugin://plugin.video.SportsDevil/?mode=1&amp;item=catcher%3dstreams%26url=https://daddylive.live/embed/stream-32.php::LISTNAME:[B][COLORorangered]Link 1 DaddyLive[/COLOR][/B]::#
	sublink:LISTSOURCE:plugin://plugin.video.SportsDevil/?mode=1&amp;item=catcher%3dstreams%26url=http://www.sports-stream.net/BT-Sport-2.html::LISTNAME:[B][COLORorangered]Link 2 sports-stream.net[/COLOR][/B]::#
	</link>
	<thumbnail>https://i.imgur.com/RjSq8t2.png</thumbnail>
	<fanart>http://sport-onthebox.com/wp-content/uploads/2016/08/BT-Sport-Generic.png</fanart>
	<summary>I DO NOT OWN OR HOST THESE STREAMING LINKS.THEY ARE FREELY AVAILABLE ON THE INTERNET.Credits to the owners</summary>
</item>

<item>
	<title>BT Sport 3</title>
	<link>
	sublink:LISTSOURCE:plugin://plugin.video.SportsDevil/?mode=1&amp;item=catcher%3dstreams%26url=http://www.sports-stream.net/BT-Sport-3.html::LISTNAME:[B][COLORorangered]Link 1 sports-stream.net/[/COLOR][/B]::#
	sublink:LISTSOURCE:plugin://plugin.video.SportsDevil/?mode=1&amp;item=catcher%3dstreams%26url=https://daddylive.live/embed/stream-33.php::LISTNAME:[B][COLORorangered]Link 2 DaddyLive[/COLOR][/B]::#
	</link>
	<thumbnail>http://mikesandroid.info/UsaLogos/BT%20SPORTS%203.png</thumbnail>
	<fanart>http://sport-onthebox.com/wp-content/uploads/2016/08/BT-Sport-Generic.png</fanart>
	<summary>I DO NOT OWN OR HOST THESE STREAMING LINKS.THEY ARE FREELY AVAILABLE ON THE INTERNET.Credits to the owners</summary>
</item>

<item>
	<title>BT Sport ESPN</title>
	<link>
	sublink:LISTSOURCE:plugin://plugin.video.SportsDevil/?mode=1&amp;item=catcher%3dstreams%26url=https://daddylive.live/embed/stream-34.php::LISTNAME:[B][COLORorangered]Link 1 | DaddyLive[/COLOR][/B]::#
	sublink:LISTSOURCE:plugin://plugin.video.SportsDevil/?mode=1&amp;item=catcher%3dstreams%26url=http://www.sports-stream.net/BT-Sport-ESPN.html::LISTNAME:[B][COLORorangered]Link 2 | sports-stream.net[/COLOR][/B]::#
	</link>
	<thumbnail>https://i.imgur.com/gbz28mw.png</thumbnail>
	<fanart>-</fanart>
	<summary>I DO NOT OWN OR HOST THESE STREAMING LINKS.THEY ARE FREELY AVAILABLE ON THE INTERNET.Credits to the owners</summary>
</item>


item>
	<title>Canal+ Sport</title>
	<link>
	sublink:LISTSOURCE:plugin://plugin.video.SportsDevil/?mode=1&amp;item=catcher%3dstreams%26url=::LISTNAME:[B][COLORorangered] 1 OffLine[/COLOR][/B]::#
	sublink:LISTSOURCE:plugin://plugin.video.SportsDevil/?mode=1&amp;item=catcher%3dstreams%26url=::LISTNAME:[B][COLORorangered] 2 OffLine[/COLOR][/B]::#
	</link>
	<thumbnail>https://upload.wikimedia.org/wikipedia/commons/0/04/Canal%2B_1991-1996_reproduction.png</thumbnail>
	<fanart>https://vignette.wikia.nocookie.net/logopedia/images/c/c2/Canal_%2B_80s.png/revision/latest?cb=20170509081408</fanart>
	<summary>I DO NOT OWN OR HOST THESE STREAMING LINKS.THEY ARE FREELY AVAILABLE ON THE INTERNET.Credits to the owners</summary>
</item>

item>
	<title>CBS SPORTS NETWORK</title>
	<link>
	sublink:LISTSOURCE:plugin://plugin.video.SportsDevil/?mode=1&amp;item=catcher%3dstreams%26url=::LISTNAME:[B][COLORorangered] 1 OffLine[/COLOR][/B]::#
	sublink:LISTSOURCE:plugin://plugin.video.SportsDevil/?mode=1&amp;item=catcher%3dstreams%26url=::LISTNAME:[B][COLORorangered] 2 OffLine[/COLOR][/B]::#
	</link>
	<thumbnail>http://vaders.tv/logos/CBS%20Sports%20Network%20HD.png</thumbnail>
	<fanart></fanart>
	<summary>I DO NOT OWN OR HOST THESE STREAMING LINKS.THEY ARE FREELY AVAILABLE ON THE INTERNET.Credits to the owners</summary>
</item>

 item>
	<title>Eleven Sport 2</title>
	<link>
	sublink:LISTSOURCE:plugin://plugin.video.SportsDevil/?mode=1&amp;item=catcher%3dstreams%26url=::LISTNAME:[B][COLORorangered] 2 OffLine[/COLOR][/B]::#
	sublink:LISTSOURCE:plugin://plugin.video.SportsDevil/?mode=1&amp;item=catcher%3dstreams%26url=::LISTNAME:[B][COLORorangered] 3 OffLine[/COLOR][/B]::#
	sublink:LISTSOURCE:plugin://plugin.video.SportsDevil/?mode=1&amp;item=catcher%3dstreams%26url=::LISTNAME:[B][COLORorangered] 4 OffLine[/COLOR][/B]::#
	</link>
    <thumbnail>https://ocdn.eu/program-tv/adm/eb2fcce4f9efb9de7e3f843de571481ac0d0d240f016a56b526f190feb889f40</thumbnail>
    <summary>I DO NOT OWN OR HOST THESE STREAMING LINKS.THEY ARE FREELY AVAILABLE ON THE INTERNET.Credits to the owners</summary>
</item>
		
<item>
	<title>ESPN 1</title>
	<link>
	sublink:LISTSOURCE:plugin://plugin.video.SportsDevil/?mode=1&amp;item=catcher%3dstreams%26url=https://daddylive.live/embed/stream-44.php::LISTNAME:[B][COLORorangered] 1 DaddyLive[/COLOR][/B]::#
	sublink:LISTSOURCE:plugin://plugin.video.SportsDevil/?mode=1&amp;item=catcher%3dstreams%26url=::LISTNAME:[B][COLORorangered] 2 OffLine[/COLOR][/B]::#
	sublink:LISTSOURCE:plugin://plugin.video.SportsDevil/?mode=1&amp;item=catcher%3dstreams%26url=::LISTNAME:[B][COLORorangered] 3 OffLine[/COLOR][/B]::#
	sublink:LISTSOURCE:plugin://plugin.video.SportsDevil/?mode=1&amp;item=catcher%3dstreams%26url=::LISTNAME:[B][COLORorangered] 4 OffLine[/COLOR][/B]::#
	</link>
	<thumbnail>http://digitalvideosystems.net/wp-content/uploads/2018/02/ESPN-Logo.png</thumbnail>
	<fanart>http://cdn1.thecomeback.com/wp-content/uploads/sites/94/2016/01/ESPN-NFL.jpeg</fanart>
	<summary>I DO NOT OWN OR HOST THESE STREAMING LINKS.THEY ARE FREELY AVAILABLE ON THE INTERNET.Credits to the owners</summary>
</item>

<item>
	<title>ESPN 2</title>
	<link>
	sublink:LISTSOURCE:plugin://plugin.video.SportsDevil/?mode=1&amp;item=catcher%3dstreams%26url=https://daddylive.live/embed/stream-45.php::LISTNAME:[B][COLORorangered] DaddyLive[/COLOR][/B]::#
	sublink:LISTSOURCE:plugin://plugin.video.SportsDevil/?mode=1&amp;item=catcher%3dstreams%26url=::LISTNAME:[B][COLORorangered] 2 OffLine[/COLOR][/B]::#
	sublink:LISTSOURCE:plugin://plugin.video.SportsDevil/?mode=1&amp;item=catcher%3dstreams%26url=::LISTNAME:[B][COLORorangered] 3 OffLine[/COLOR][/B]::#
	sublink:LISTSOURCE:plugin://plugin.video.SportsDevil/?mode=1&amp;item=catcher%3dstreams%26url=::LISTNAME:[B][COLORorangered] 4 OffLine[/COLOR][/B]::#
	</link>
	<thumbnail>https://upload.wikimedia.org/wikipedia/commons/thumb/b/bf/ESPN2_logo.svg/2000px-ESPN2_logo.svg.png</thumbnail>
	<fanart></fanart>
	<summary>I DO NOT OWN OR HOST THESE STREAMING LINKS.THEY ARE FREELY AVAILABLE ON THE INTERNET.Credits to the owners</summary>
</item>


item>
	<title>ESPN Deportes</title>
	<link>
	sublink:LISTSOURCE:plugin://plugin.video.SportsDevil/?mode=1&amp;item=catcher%3dstreams%26url=::LISTNAME:[B][COLORorangered] 1 OffLine[/COLOR][/B]::#
	sublink:LISTSOURCE:plugin://plugin.video.SportsDevil/?mode=1&amp;item=catcher%3dstreams%26url=::LISTNAME:[B][COLORorangered] 2 OffLine[/COLOR][/B]::#
	sublink:LISTSOURCE:plugin://plugin.video.SportsDevil/?mode=1&amp;item=catcher%3dstreams%26url=::LISTNAME:[B][COLORorangered] 3 OffLine[/COLOR][/B]::#
	sublink:LISTSOURCE:plugin://plugin.video.SportsDevil/?mode=1&amp;item=catcher%3dstreams%26url=::LISTNAME:[B][COLORorangered] 4 OffLine[/COLOR][/B]::#
	</link>
	<thumbnail>https://sc.dish.com/shared/images/station-logos/espnd.png</thumbnail>
	<fanart></fanart>
	<summary>I DO NOT OWN OR HOST THESE STREAMING LINKS.THEY ARE FREELY AVAILABLE ON THE INTERNET.Credits to the owners</summary>
</item>

item>
	<title>ESPN News | OffLine</title>
	<link>
	sublink:LISTSOURCE:plugin://plugin.video.SportsDevil/?mode=1&amp;item=catcher%3dstreams%26url=::LISTNAME:[B][COLORorangered]Link 1 OFFLINE[/COLOR][/B]::#
	sublink:LISTSOURCE:plugin://plugin.video.SportsDevil/?mode=1&amp;item=catcher%3dstreams%26url=::LISTNAME:[B][COLORorangered]Link 2 OFFLINE[/COLOR][/B]::#
	</link>
	<thumbnail>http://www.jedschwartz.com/JSPhome/Broadpage/ESPN/ESPNEWS.jpg</thumbnail>
	<fanart></fanart>
	<summary>I DO NOT OWN OR HOST THESE STREAMING LINKS.THEY ARE FREELY AVAILABLE ON THE INTERNET.Credits to the owners</summary>
</item>

item>
      <title>[B]ESPN | UK | Offline[/B]</title>
      <link>
	  sublink:LISTSOURCE:plugin://plugin.video.SportsDevil/?mode=1&amp;item=catcher%3dstreams%26url=::LISTNAME:[B][COLORorangered]Link 1 OFFLINE[/COLOR][/B]::#
	  sublink:LISTSOURCE:plugin://plugin.video.SportsDevil/?mode=1&amp;item=catcher%3dstreams%26url=::LISTNAME:[B][COLORorangered]Link 2 OFFLINE[/COLOR][/B]::#
      </link>
      <thumbnail>https://archive.org/download/tvlogos/ESPN2.png</thumbnail>
      <fanart>http://cdn1.thecomeback.com/wp-content/uploads/sites/94/2016/01/ESPN-NFL.jpeg</fanart>
<item>



<item>
	<title>EuroSport 1</title>
	<link>
    sublink:LISTSOURCE:plugin://plugin.video.SportsDevil/?mode=1&amp;item=catcher%3dstreams%26url=https://daddylive.live/embed/stream-41.php::LISTNAME:[B][COLORorangered]Link 1[/COLOR][/B]::#
	sublink:LISTSOURCE:plugin://plugin.video.SportsDevil/?mode=1&amp;item=catcher%3dstreams%26url=::LISTNAME:[B][COLORorangered]Link 2 OFFLINE[/COLOR][/B]::#
	sublink:LISTSOURCE:plugin://plugin.video.SportsDevil/?mode=1&amp;item=catcher%3dstreams%26url=::LISTNAME:[B][COLORorangered]Link 3 OFFLINE[/COLOR][/B]::#
	</link>
	<thumbnail>https://upload.wikimedia.org/wikipedia/commons/a/a2/ESP_GGS_RVB.png</thumbnail>
	<fanart></fanart>
	<summary>I DO NOT OWN OR HOST THESE STREAMING LINKS.THEY ARE FREELY AVAILABLE ON THE INTERNET.Credits to the owners</summary>
</item>

<item>
	<title>EuroSport 2</title>
	<link>
	sublink:LISTSOURCE:plugin://plugin.video.SportsDevil/?mode=1&amp;item=catcher%3dstreams%26url=::LISTNAME:[B][COLORorangered]Link 1 OFFLINE[/COLOR][/B]::#
	sublink:LISTSOURCE:plugin://plugin.video.SportsDevil/?mode=1&amp;item=catcher%3dstreams%26url=::LISTNAME:[B][COLORorangered]Link 2 OFFLINE[/COLOR][/B]::#
	sublink:LISTSOURCE:plugin://plugin.video.SportsDevil/?mode=1&amp;item=catcher%3dstreams%26url=https://daddylive.live/embed/stream-42.php::LISTNAME:[B][COLORorangered]Link 3 | daddylive[/COLOR][/B]::#
	</link>
	<thumbnail>https://vignette.wikia.nocookie.net/logopedia/images/c/cb/Eurosport_2_HD.svg/revision/latest/scale-to-width-down/640?cb=20171123164013</thumbnail>
	<fanart>-</fanart>
	<summary>I DO NOT OWN OR HOST THESE STREAMING LINKS.THEY ARE FREELY AVAILABLE ON THE INTERNET.Credits to the owners</summary>
</item>

item>
	<title>Fox Sports</title>
	<link>
	sublink:LISTSOURCE:plugin://plugin.video.SportsDevil/?mode=1&amp;item=catcher%3dstreams%26url=::LISTNAME:[B][COLORorangered]Link OffLine[/COLOR][/B]::#
	sublink:LISTSOURCE:plugin://plugin.video.SportsDevil/?mode=1&amp;item=catcher%3dstreams%26url=::LISTNAME:[B][COLORorangered]Link OffLine[/COLOR][/B]::#
	</link>
	<thumbnail>https://vignette.wikia.nocookie.net/logopedia/images/6/6f/Logo_fox_sports.png/revision/latest?cb=20140414164158</thumbnail>
	<fanart>-</fanart>
	<summary>I DO NOT OWN OR HOST THESE STREAMING LINKS.THEY ARE FREELY AVAILABLE ON THE INTERNET.Credits to the owners</summary>
</item>

<item>
	<title>Fox Sports 1 USA</title>
	<link>
	sublink:LISTSOURCE:plugin://plugin.video.SportsDevil/?mode=1&amp;item=catcher%3dstreams%26url=::LISTNAME:[B][COLORorangered]Link 1 OFFLINE[/COLOR][/B]::#
	sublink:LISTSOURCE:plugin://plugin.video.SportsDevil/?mode=1&amp;item=catcher%3dstreams%26url=https://daddylive.live/embed/stream-39.php::LISTNAME:[B][COLORorangered]Link 2|daddylive[/COLOR][/B]::#
	</link>
	<thumbnail>http://cdn1.thecomeback.com/wp-content/uploads/sites/94/2015/09/Screen-Shot-2015-09-04-at-6.09.55-PM.png</thumbnail>
	<fanart>https://static.nascar.com/content/dam/nascar/articles/2016/Non-date-specific-images/NewTVmain-2.jpg/jcr:content/renditions/original</fanart>
	<summary>I DO NOT OWN OR HOST THESE STREAMING LINKS.THEY ARE FREELY AVAILABLE ON THE INTERNET.Credits to the owners</summary>
</item>

item>
	<title>Fox Sports 2 USA</title>
	<link>
	sublink:LISTSOURCE:plugin://plugin.video.SportsDevil/?mode=1&amp;item=catcher%3dstreams%26url=::LISTNAME:[B][COLORorangered]Link 1 OFFLINE[/COLOR][/B]::#
	sublink:LISTSOURCE:plugin://plugin.video.SportsDevil/?mode=1&amp;item=catcher%3dstreams%26url=::LISTNAME:[B][COLORorangered]Link 2 OFFLINE[/COLOR][/B]::#
	</link>
	<thumbnail>https://upload.wikimedia.org/wikipedia/commons/thumb/3/38/FS2_logo_2015.svg/1200px-FS2_logo_2015.svg.png</thumbnail>
	<fanart>https://newyorkcity-mp7static.mlsdigital.net/images/Screen%20Shot%202016-04-23%20at%202.11.24%20PM.png?Pd8Kflf0DhLkVcfVu31wkq0WXrhXNCoW</fanart>
	<summary>I DO NOT OWN OR HOST THESE STREAMING LINKS.THEY ARE FREELY AVAILABLE ON THE INTERNET.Credits to the owners</summary>
</item>

item>
	<title>Fox North</title>
	<link>
	sublink:LISTSOURCE:plugin://plugin.video.SportsDevil/?mode=1&amp;item=catcher%3dstreams%26url=::LISTNAME:[B][COLORorangered]Link 1 OFFLINE[/COLOR][/B]::#
	sublink:LISTSOURCE:plugin://plugin.video.SportsDevil/?mode=1&amp;item=catcher%3dstreams%26url=::LISTNAME:[B][COLORorangered]Link 2 OFFLINE[/COLOR][/B]::#
	</link>
	<thumbnail>https://upload.wikimedia.org/wikipedia/en/thumb/b/b0/Fox_Sports_North_2012_logo.png/200px-Fox_Sports_North_2012_logo.png</thumbnail>
	<fanart>-</fanart>
	<summary>I DO NOT OWN OR HOST THESE STREAMING LINKS.THEY ARE FREELY AVAILABLE ON THE INTERNET.Credits to the owners</summary>
</item>


<item>
	<title>MLB Network</title>
	<link>
	sublink:LISTSOURCE:plugin://plugin.video.SportsDevil/?mode=1&amp;item=catcher%3dstreams%26url=::LISTNAME:[B][COLORorangered]Link 1| OFFLINE[/COLOR][/B]::#
	sublink:LISTSOURCE:plugin://plugin.video.SportsDevil/?mode=1&amp;item=catcher%3dstreams%26url=::LISTNAME:[B][COLORorangered]Link 2| OFFLINE[/COLOR][/B]::#
	sublink:LISTSOURCE:plugin://plugin.video.SportsDevil/?mode=1&amp;item=catcher%3dstreams%26url=http://www.720pstream.me/mlb-network-live-stream|User-Agent=Mozilla/5.0 (Windows NT 10.0; Win64; x64) AppleWebKit/537.36 (KHTML, like Gecko) Chrome/65.0.3325.181 Safari/537.36::LISTNAME:[B][COLORorangered]Link 3| 720pstream[/COLOR][/B]::#
	sublink:LISTSOURCE:plugin://plugin.video.SportsDevil/?mode=1&amp;item=catcher%3dstreams%26url=::LISTNAME:[B][COLORorangered]Link 4 OFFLINE[/COLOR][/B]::#
	sublink:LISTSOURCE:plugin://plugin.video.SportsDevil/?mode=1&amp;item=catcher%3dstreams%26url=::LISTNAME:[B][COLORorangered]Link 5 OFFLINE[/COLOR][/B]::#
	</link>
	<thumbnail>https://upload.wikimedia.org/wikipedia/en/thumb/a/ac/MLBNetworkLogo.svg/383px-MLBNetworkLogo.svg.png</thumbnail>
	<fanart>-</fanart>
	<summary>I DO NOT OWN OR HOST THESE STREAMING LINKS.THEY ARE FREELY AVAILABLE ON THE INTERNET.Credits to the owners</summary>
</item>

item>
	<title>[B]Moto GP[/B]</title>
	<link>
	sublink:LISTSOURCE:plugin://plugin.video.SportsDevil/?mode=1&amp;item=catcher%3dstreams%26url=::LISTNAME:[B][COLORorangered]Link 1 OFFLINE[/COLOR][/B]::#
	sublink:LISTSOURCE:plugin://plugin.video.SportsDevil/?mode=1&amp;item=catcher%3dstreams%26url=::LISTNAME:[B][COLORorangered]Link 2 OFFLINE[/COLOR][/B]::#
	</link>
	<thumbnail>http://lacalleochotv.org/wp-content/uploads/motogpp.jpg</thumbnail>
	<fanart>-</fanart>
	<summary>I DO NOT OWN OR HOST THESE STREAMING LINKS.THEY ARE FREELY AVAILABLE ON THE INTERNET.Credits to the owners</summary>
</item>


item>
	<title>NBA TV</title>
	<link>
	sublink:LISTSOURCE:plugin://plugin.video.SportsDevil/?mode=1&amp;item=catcher%3dstreams%26url=::LISTNAME:[B][COLORorangered]Link 1 OFFLINE[/COLOR][/B]::#
	sublink:LISTSOURCE:plugin://plugin.video.SportsDevil/?mode=1&amp;item=catcher%3dstreams%26url=::LISTNAME:[B][COLORorangered]Link 2 OFFLINE[/COLOR][/B]::#
	</link>
	<thumbnail>https://archive.org/download/tvlogos/NBA%20TV.png</thumbnail>
	<fanart>-</fanart>
	<summary>I DO NOT OWN OR HOST THESE STREAMING LINKS.THEY ARE FREELY AVAILABLE ON THE INTERNET.Credits to the owners</summary>
</item>

<item>
	<title>NHL TV</title>
	<link>
	sublink:LISTSOURCE:plugin://plugin.video.SportsDevil/?mode=1&amp;item=catcher%3dstreams%26url=::LISTNAME:[B][COLORorangered]Link 1 OFFLINE[/COLOR][/B]::#
	sublink:LISTSOURCE:plugin://plugin.video.SportsDevil/?mode=1&amp;item=catcher%3dstreams%26url=::LISTNAME:[B][COLORorangered]Link 2 OFFLINE[/COLOR][/B]::#
	</link>
	<thumbnail>https://i.ibb.co/pv9L5s6/images.png</thumbnail>
	<fanart>-</fanart>
	<summary>I DO NOT OWN OR HOST THESE STREAMING LINKS.THEY ARE FREELY AVAILABLE ON THE INTERNET.Credits to the owners</summary>
</item>

<item>
	<title>NBCSN USA</title>
	<link>
	sublink:LISTSOURCE:plugin://plugin.video.SportsDevil/?mode=1&amp;item=catcher%3dstreams%26url=https://daddylive.live/embed/stream-43.php::LISTNAME:[B][COLORorangered]Link 1 | daddylive[/COLOR][/B]::#
	sublink:LISTSOURCE:plugin://plugin.video.SportsDevil/?mode=1&amp;item=catcher%3dstreams%26url=::LISTNAME:[B][COLORorangered]Link 2 | OFFLINE[/COLOR][/B]::#
	</link>
	<thumbnail>http://epg-image.totsuko.tv/epg-images/channel/25159/nbcsn_440x330_NETWORK_LARGE_440_330.png</thumbnail>
	<fanart>-</fanart>
	<summary>I DO NOT OWN OR HOST THESE STREAMING LINKS.THEY ARE FREELY AVAILABLE ON THE INTERNET.Credits to the owners</summary>
</item>

item>
	<title>NFL-Network</title>
	<link>
	sublink:LISTSOURCE:plugin://plugin.video.SportsDevil/?mode=1&amp;item=catcher%3dstreams%26url=::LISTNAME:[B][COLORorangered]Link 1 OFFLINE[/COLOR][/B]::#
	sublink:LISTSOURCE:plugin://plugin.video.SportsDevil/?mode=1&amp;item=catcher%3dstreams%26url=::LISTNAME:[B][COLORorangered]Link 2 OFFLINE[/COLOR][/B]::#
	</link>
	<thumbnail>https://vignette.wikia.nocookie.net/logopedia/images/7/75/Nfl-network-logo.jpg/revision/latest?cb=20150809205413</thumbnail>
	<fanart>-</fanart>
	<summary>I DO NOT OWN OR HOST THESE STREAMING LINKS.THEY ARE FREELY AVAILABLE ON THE INTERNET.Credits to the owners</summary>
</item>

item>
	<title>NFL Alternate </title>
	<link>
	sublink:LISTSOURCE:plugin://plugin.video.SportsDevil/?mode=1&amp;item=catcher%3dstreams%26url=::LISTNAME:[B][COLORorangered]Link 1 OFFLINE[/COLOR][/B]::#
	sublink:LISTSOURCE:plugin://plugin.video.SportsDevil/?mode=1&amp;item=catcher%3dstreams%26url=::LISTNAME:[B][COLORorangered]Link 2 OFFLINE[/COLOR][/B]::#
	</link>
	<thumbnail>http://wallpapercave.com/wp/jXLRtK5.jpg</thumbnail>
	<fanart>-</fanart>
	<summary>I DO NOT OWN OR HOST THESE STREAMING LINKS.THEY ARE FREELY AVAILABLE ON THE INTERNET.Credits to the owners</summary>
</item>

item>
	<title>NFL Alternate II</title>
	<link>
	sublink:LISTSOURCE:plugin://plugin.video.SportsDevil/?mode=1&amp;item=catcher%3dstreams%26url=::LISTNAME:[B][COLORorangered]Link 1 OFFLINE[/COLOR][/B]::#
	sublink:LISTSOURCE:plugin://plugin.video.SportsDevil/?mode=1&amp;item=catcher%3dstreams%26url=::LISTNAME:[B][COLORorangered]Link 2 OFFLINE[/COLOR][/B]::#
	</link>
	<thumbnail>http://wallpapercave.com/wp/jXLRtK5.jpg</thumbnail>
	<fanart>-</fanart>
	<summary>I DO NOT OWN OR HOST THESE STREAMING LINKS.THEY ARE FREELY AVAILABLE ON THE INTERNET.Credits to the owners</summary>
</item>

item>
	<title>NFL Now</title>
	<link>
	sublink:LISTSOURCE:plugin://plugin.video.SportsDevil/?mode=1&amp;item=catcher%3dstreams%26url=::LISTNAME:[B][COLORorangered]Link 1 OFFLINE[/COLOR][/B]::#
	sublink:LISTSOURCE:plugin://plugin.video.SportsDevil/?mode=1&amp;item=catcher%3dstreams%26url=::LISTNAME:[B][COLORorangered]Link 2 OFFLINE[/COLOR][/B]::#
	</link>
	<thumbnail>https://tse1.mm.bing.net/th?id=OIP.aZWSPP-iaUdVrNqv4py7pwHaFk&w=115&h=105&c=8&rs=1&qlt=90&pid=3.1&rm=2</thumbnail>
	<fanart>-</fanart>
	<summary>I DO NOT OWN OR HOST THESE STREAMING LINKS.THEY ARE FREELY AVAILABLE ON THE INTERNET.Credits to the owners</summary>
</item>

item>
	<title>NFL Now HD</title>
	<link>
	sublink:LISTSOURCE:plugin://plugin.video.SportsDevil/?mode=1&amp;item=catcher%3dstreams%26url=::LISTNAME:[B][COLORorangered]Link 1 OFFLINE[/COLOR][/B]::#
	sublink:LISTSOURCE:plugin://plugin.video.SportsDevil/?mode=1&amp;item=catcher%3dstreams%26url=::LISTNAME:[B][COLORorangered]Link 2 OFFLINE[/COLOR][/B]::#
	</link>
	<thumbnail>https://tse1.mm.bing.net/th?id=OIP.aZWSPP-iaUdVrNqv4py7pwHaFk&w=115&h=105&c=8&rs=1&qlt=90&pid=3.1&rm=2</thumbnail>
	<fanart>-</fanart>
	<summary>I DO NOT OWN OR HOST THESE STREAMING LINKS.THEY ARE FREELY AVAILABLE ON THE INTERNET.Credits to the owners</summary>
</item>

item>
<title>2018 Olympics - Channel 1</title>
<link>
	sublink:LISTSOURCE:plugin://plugin.video.SportsDevil/?mode=1&amp;item=catcher%3dstreams%26url=::LISTNAME:[B][COLORorangered]Link 1 OFFLINE[/COLOR][/B]::#
	sublink:LISTSOURCE:plugin://plugin.video.SportsDevil/?mode=1&amp;item=catcher%3dstreams%26url=::LISTNAME:[B][COLORorangered]Link 2 OFFLINE[/COLOR][/B]::#
</link>
<thumnail>http://www.thebusinessofsports.com/wp-content/uploads/2011/06/nbc-olympics-logo-060711.jpg</thumnail>
<fanart>https://lovelace-media.imgix.net/getty/585266596.jpg</fanart>
</item>

item>
<title>2018 Olympics - Channel 2</title>
<link>
	sublink:LISTSOURCE:plugin://plugin.video.SportsDevil/?mode=1&amp;item=catcher%3dstreams%26url=::LISTNAME:[B][COLORorangered]Link 1 OFFLINE[/COLOR][/B]::#
	sublink:LISTSOURCE:plugin://plugin.video.SportsDevil/?mode=1&amp;item=catcher%3dstreams%26url=::LISTNAME:[B][COLORorangered]Link 2 OFFLINE[/COLOR][/B]::#
</link>
<thumnail>http://www.thebusinessofsports.com/wp-content/uploads/2011/06/nbc-olympics-logo-060711.jpg</thumnail>
<fanart>https://lovelace-media.imgix.net/getty/585266596.jpg</fanart>
</item>

item>
<title>2018 Olympics - Channel 3</title>
<link>
	sublink:LISTSOURCE:plugin://plugin.video.SportsDevil/?mode=1&amp;item=catcher%3dstreams%26url=::LISTNAME:[B][COLORorangered]Link 1 OFFLINE[/COLOR][/B]::#
	sublink:LISTSOURCE:plugin://plugin.video.SportsDevil/?mode=1&amp;item=catcher%3dstreams%26url=::LISTNAME:[B][COLORorangered]Link 2 OFFLINE[/COLOR][/B]::#
</link>
<thumnail>http://www.thebusinessofsports.com/wp-content/uploads/2011/06/nbc-olympics-logo-060711.jpg</thumnail>
<fanart>https://lovelace-media.imgix.net/getty/585266596.jpg</fanart>
</item>

item>
<title>2018 Olympics - Channel 4</title>
<link>
	sublink:LISTSOURCE:plugin://plugin.video.SportsDevil/?mode=1&amp;item=catcher%3dstreams%26url=::LISTNAME:[B][COLORorangered]Link 1 OFFLINE[/COLOR][/B]::#
	sublink:LISTSOURCE:plugin://plugin.video.SportsDevil/?mode=1&amp;item=catcher%3dstreams%26url=::LISTNAME:[B][COLORorangered]Link 2 OFFLINE[/COLOR][/B]::#
</link>
<thumnail>http://www.thebusinessofsports.com/wp-content/uploads/2011/06/nbc-olympics-logo-060711.jpg</thumnail>
<fanart>https://lovelace-media.imgix.net/getty/585266596.jpg</fanart>
</item>

item>
<title>2018 Olympics - Channel 5</title>
<link>
	sublink:LISTSOURCE:plugin://plugin.video.SportsDevil/?mode=1&amp;item=catcher%3dstreams%26url=::LISTNAME:[B][COLORorangered]Link 1 OFFLINE[/COLOR][/B]::#
	sublink:LISTSOURCE:plugin://plugin.video.SportsDevil/?mode=1&amp;item=catcher%3dstreams%26url=::LISTNAME:[B][COLORorangered]Link 2 OFFLINE[/COLOR][/B]::#
</link>
<thumnail>http://www.thebusinessofsports.com/wp-content/uploads/2011/06/nbc-olympics-logo-060711.jpg</thumnail>
<fanart>https://lovelace-media.imgix.net/getty/585266596.jpg</fanart>
</item>

item>
	<title>PAC 12 Arizona</title>
	<link>
	sublink:LISTSOURCE:plugin://plugin.video.SportsDevil/?mode=1&amp;item=catcher%3dstreams%26url=::LISTNAME:[B][COLORorangered]Link 1 OFFLINE[/COLOR][/B]::#
	sublink:LISTSOURCE:plugin://plugin.video.SportsDevil/?mode=1&amp;item=catcher%3dstreams%26url=::LISTNAME:[B][COLORorangered]Link 2 OFFLINE[/COLOR][/B]::#
	</link>
	<thumbnail>https://archive.org/download/tvlogos/PAC-12%20Arizona.png</thumbnail>
	<fanart>-</fanart>
	<summary>I DO NOT OWN OR HOST THESE STREAMING LINKS.THEY ARE FREELY AVAILABLE ON THE INTERNET.Credits to the owners</summary>
</item>

item>
	<title>PAC 12 Bay Area</title>
	<link>
	sublink:LISTSOURCE:plugin://plugin.video.SportsDevil/?mode=1&amp;item=catcher%3dstreams%26url=::LISTNAME:[B][COLORorangered]Link 1 OFFLINE[/COLOR][/B]::#
	sublink:LISTSOURCE:plugin://plugin.video.SportsDevil/?mode=1&amp;item=catcher%3dstreams%26url=::LISTNAME:[B][COLORorangered]Link 2 OFFLINE[/COLOR][/B]::#
	</link>
	<thumbnail>https://archive.org/download/tvlogos/PAC-12%20Bay%20Area.png</thumbnail>
	<fanart>-</fanart>
	<summary>I DO NOT OWN OR HOST THESE STREAMING LINKS.THEY ARE FREELY AVAILABLE ON THE INTERNET.Credits to the owners</summary>
</item>

item>
	<title>PAC 12 L.A.</title>
	<link>
	sublink:LISTSOURCE:plugin://plugin.video.SportsDevil/?mode=1&amp;item=catcher%3dstreams%26url=::LISTNAME:[B][COLORorangered]Link 1 OFFLINE[/COLOR][/B]::#
	sublink:LISTSOURCE:plugin://plugin.video.SportsDevil/?mode=1&amp;item=catcher%3dstreams%26url=::LISTNAME:[B][COLORorangered]Link 2 OFFLINE[/COLOR][/B]::#
	</link>
	<thumbnail>https://archive.org/download/tvlogos/PAC-12%20Los%20Angeles.png</thumbnail>
	<fanart>-</fanart>
	<summary>I DO NOT OWN OR HOST THESE STREAMING LINKS.THEY ARE FREELY AVAILABLE ON THE INTERNET.Credits to the owners</summary>
</item>

item>
	<title>PAC 12 Mountain</title>
	<link>
	sublink:LISTSOURCE:plugin://plugin.video.SportsDevil/?mode=1&amp;item=catcher%3dstreams%26url=::LISTNAME:[B][COLORorangered]Link 1 OFFLINE[/COLOR][/B]::#
	sublink:LISTSOURCE:plugin://plugin.video.SportsDevil/?mode=1&amp;item=catcher%3dstreams%26url=::LISTNAME:[B][COLORorangered]Link 2 OFFLINE[/COLOR][/B]::#
	</link>
	<thumbnail>https://archive.org/download/tvlogos/PAC-12%20Mountain.png</thumbnail>
	<fanart>-</fanart>
	<summary>I DO NOT OWN OR HOST THESE STREAMING LINKS.THEY ARE FREELY AVAILABLE ON THE INTERNET.Credits to the owners</summary>
</item>

item>
	<title>PAC 12 National</title>
	<link>
	sublink:LISTSOURCE:plugin://plugin.video.SportsDevil/?mode=1&amp;item=catcher%3dstreams%26url=::LISTNAME:[B][COLORorangered]Link 1 OFFLINE[/COLOR][/B]::#
	sublink:LISTSOURCE:plugin://plugin.video.SportsDevil/?mode=1&amp;item=catcher%3dstreams%26url=::LISTNAME:[B][COLORorangered]Link 2 OFFLINE[/COLOR][/B]::#
	</link>
	<thumbnail>https://archive.org/download/tvlogos/PAC-12%20Network.png</thumbnail>
	<fanart>-</fanart>
	<summary>I DO NOT OWN OR HOST THESE STREAMING LINKS.THEY ARE FREELY AVAILABLE ON THE INTERNET.Credits to the owners</summary>
</item>

item>
	<title>PAC 12 Network (down)</title>
	<link>
	sublink:LISTSOURCE:plugin://plugin.video.SportsDevil/?mode=1&amp;item=catcher%3dstreams%26url=::LISTNAME:[B][COLORorangered]Link 1 OFFLINE[/COLOR][/B]::#
	sublink:LISTSOURCE:plugin://plugin.video.SportsDevil/?mode=1&amp;item=catcher%3dstreams%26url=::LISTNAME:[B][COLORorangered]Link 2 OFFLINE[/COLOR][/B]::#
	</link>
	<thumbnail>https://archive.org/download/tvlogos/PAC-12%20Network.png</thumbnail>
	<fanart>-</fanart>
	<summary>I DO NOT OWN OR HOST THESE STREAMING LINKS.THEY ARE FREELY AVAILABLE ON THE INTERNET.Credits to the owners</summary>
</item>

item>
	<title>PAC 12 Oregon</title>
	<link>
	sublink:LISTSOURCE:plugin://plugin.video.SportsDevil/?mode=1&amp;item=catcher%3dstreams%26url=::LISTNAME:[B][COLORorangered]Link 1 OFFLINE[/COLOR][/B]::#
	sublink:LISTSOURCE:plugin://plugin.video.SportsDevil/?mode=1&amp;item=catcher%3dstreams%26url=::LISTNAME:[B][COLORorangered]Link 2 OFFLINE[/COLOR][/B]::#
	</link>
	<thumbnail>https://archive.org/download/tvlogos/PAC-12%20Oregon.png</thumbnail>
	<fanart>-</fanart>
	<summary>I DO NOT OWN OR HOST THESE STREAMING LINKS.THEY ARE FREELY AVAILABLE ON THE INTERNET.Credits to the owners</summary>
</item>

item>
	<title>PAC 12 Washington</title>
	<link>
	sublink:LISTSOURCE:plugin://plugin.video.SportsDevil/?mode=1&amp;item=catcher%3dstreams%26url=::LISTNAME:[B][COLORorangered]Link 1 OFFLINE[/COLOR][/B]::#
	sublink:LISTSOURCE:plugin://plugin.video.SportsDevil/?mode=1&amp;item=catcher%3dstreams%26url=::LISTNAME:[B][COLORorangered]Link 2 OFFLINE[/COLOR][/B]::#
	</link>
	<thumbnail>https://archive.org/download/tvlogos/PAC-12%20Washington.png</thumbnail>
	<fanart>-</fanart>
	<summary>I DO NOT OWN OR HOST THESE STREAMING LINKS.THEY ARE FREELY AVAILABLE ON THE INTERNET.Credits to the owners</summary>
</item>

item>
	<title>Poker Central</title>
	<link>
	sublink:LISTSOURCE:plugin://plugin.video.SportsDevil/?mode=1&amp;item=catcher%3dstreams%26url=::LISTNAME:[B][COLORorangered]Link 1 OFFLINE[/COLOR][/B]::#
	sublink:LISTSOURCE:plugin://plugin.video.SportsDevil/?mode=1&amp;item=catcher%3dstreams%26url=::LISTNAME:[B][COLORorangered]Link 2 OFFLINE[/COLOR][/B]::#
	</link>
	<thumbnail>https://www.pokercentral.com/wp-content/uploads/2018/03/Poker-Central-Logo.png</thumbnail>
	<fanart>-</fanart>
	<summary>I DO NOT OWN OR HOST THESE STREAMING LINKS.THEY ARE FREELY AVAILABLE ON THE INTERNET.Credits to the owners</summary>
</item>


item>
	<title>Premier Sports</title>
	<link>
	sublink:LISTSOURCE:plugin://plugin.video.SportsDevil/?mode=1&amp;item=catcher%3dstreams%26url=::LISTNAME:[B][COLORorangered]Link 1 OFFLINE[/COLOR][/B]::#
	sublink:LISTSOURCE:plugin://plugin.video.SportsDevil/?mode=1&amp;item=catcher%3dstreams%26url=::LISTNAME:[B][COLORorangered]Link 2 OFFLINE[/COLOR][/B]::#
	</link>
	<thumbnail>https://i.imgur.com/w3H6P0G.png</thumbnail>
	<fanart>-</fanart>
	<summary>I DO NOT OWN OR HOST THESE STREAMING LINKS.THEY ARE FREELY AVAILABLE ON THE INTERNET.Credits to the owners</summary>
</item>

item>
	<title>Premier League Live</title>
	<link>
	sublink:LISTSOURCE:plugin://plugin.video.SportsDevil/?mode=1&amp;item=catcher%3dstreams%26url=::LISTNAME:[B][COLORorangered]Link 1 OFFLINE[/COLOR][/B]::#
	sublink:LISTSOURCE:plugin://plugin.video.SportsDevil/?mode=1&amp;item=catcher%3dstreams%26url=::LISTNAME:[B][COLORorangered]Link 2 OFFLINE[/COLOR][/B]::#
	</link>
	<thumbnail>https://3.bp.blogspot.com/-clqQEGqdiuc/Vrm5wXct7RI/AAAAAAAA31E/G2PmcAArZ78/s0/New-Premier-League-Logo-Revealed%2B%25282%2529.jpg</thumbnail>
	<fanart>https://upload.wikimedia.org/wikipedia/en/thumb/f/f2/Premier_League_Logo.svg/1200px-Premier_League_Logo.svg.png</fanart>
	<summary>I DO NOT OWN OR HOST THESE STREAMING LINKS.THEY ARE FREELY AVAILABLE ON THE INTERNET.Credits to the owners</summary>
</item>

item>
	<title>Racing UK</title>
	<link>
	sublink:LISTSOURCE:plugin://plugin.video.SportsDevil/?mode=1&amp;item=catcher%3dstreams%26url=::LISTNAME:[B][COLORorangered]Link 1 OFFLINE[/COLOR][/B]::#
	sublink:LISTSOURCE:plugin://plugin.video.SportsDevil/?mode=1&amp;item=catcher%3dstreams%26url=::LISTNAME:[B][COLORorangered]Link 2 OFFLINE[/COLOR][/B]::#
	</link>
	<thumbnail>https://archive.org/download/tvlogos/Racing%20UK.png</thumbnail>
	<fanart>-</fanart>
	<summary>I DO NOT OWN OR HOST THESE STREAMING LINKS.THEY ARE FREELY AVAILABLE ON THE INTERNET.Credits to the owners</summary>
</item>

<item>
	<title>Real Madrid TV</title>
	<link>
	sublink:LISTSOURCE:plugin://plugin.video.SportsDevil/?mode=1&amp;item=catcher%3dstreams%26url=::LISTNAME:[B][COLORorangered]Link 1 OFFLINE[/COLOR][/B]::#
	sublink:LISTSOURCE:plugin://plugin.video.SportsDevil/?mode=1&amp;item=catcher%3dstreams%26url=::LISTNAME:[B][COLORorangered]Link 2 OFFLINE[/COLOR][/B]::#
	sublink:LISTSOURCE:http://rmtv24hweblive-lh.akamaihd.net/i/rmtv24hweben_1@300662/index_3_av-b.m3u8::LISTNAME:[B][COLORorangered]Link 3 ONLINE[/COLOR][/B]::#
	</link>
	<thumbnail>http://directostv.teleame.com/wp-content/uploads/2016/05/Real-Madrid-TV.png</thumbnail>
	<fanart>-</fanart>
	<summary>I DO NOT OWN OR HOST THESE STREAMING LINKS.THEY ARE FREELY AVAILABLE ON THE INTERNET.Credits to the owners</summary>
</item>

item>
	<title>Setanta Sports+</title>
	<link>
	sublink:LISTSOURCE:plugin://plugin.video.SportsDevil/?mode=1&amp;item=catcher%3dstreams%26url=::LISTNAME:[B][COLORorangered]Link 1 OFFLINE[/COLOR][/B]::#
	sublink:LISTSOURCE:plugin://plugin.video.SportsDevil/?mode=1&amp;item=catcher%3dstreams%26url=::LISTNAME:[B][COLORorangered]Link 2 OFFLINE[/COLOR][/B]::#
	</link>
	<thumbnail>https://www.arax.md/assets/channels/229.png</thumbnail>
	<fanart>-</fanart>
	<summary>I DO NOT OWN OR HOST THESE STREAMING LINKS.THEY ARE FREELY AVAILABLE ON THE INTERNET.Credits to the owners</summary>
</item>

item>
	<title>EURASIA:Sky Setanta Sports</title>
	<link>
	sublink:LISTSOURCE:plugin://plugin.video.SportsDevil/?mode=1&amp;item=catcher%3dstreams%26url=::LISTNAME:[B][COLORorangered]Link 1 OFFLINE[/COLOR][/B]::#
	sublink:LISTSOURCE:plugin://plugin.video.SportsDevil/?mode=1&amp;item=catcher%3dstreams%26url=::LISTNAME:[B][COLORorangered]Link 2 OFFLINE[/COLOR][/B]::#
	</link>
	<thumbnail>https://upload.wikimedia.org/wikipedia/commons/thumb/5/5d/Setanta-logo.jpg/220px-Setanta-logo.jpg</thumbnail>
	<fanart>-</fanart>
	<summary>I DO NOT OWN OR HOST THESE STREAMING LINKS.THEY ARE FREELY AVAILABLE ON THE INTERNET.Credits to the owners</summary>
</item>

<item>
	<title>Sky Sports Action</title>
	<link>
	sublink:LISTSOURCE:plugin://plugin.video.SportsDevil/?mode=1&amp;item=catcher%3dstreams%26url=https://daddylive.live/embed/stream-37.php::LISTNAME:[B][COLORorangered]Link Daddylive[/COLOR][/B]::#
	sublink:LISTSOURCE:plugin://plugin.video.SportsDevil/?mode=1&amp;item=catcher%3dstreams%26url=::LISTNAME:[B][COLORorangered]Link OFFLINE[/COLOR][/B]::#
	</link>
	<thumbnail>https://i.imgur.com/gXOK2rK.png</thumbnail>
	<fanart>-</fanart>
	<summary>I DO NOT OWN OR HOST THESE STREAMING LINKS.THEY ARE FREELY AVAILABLE ON THE INTERNET.Credits to the owners</summary>
</item>

<item>
	<title>Sky Sports Arena</title>
	<link>
	sublink:LISTSOURCE:plugin://plugin.video.SportsDevil/?mode=1&amp;item=catcher%3dstreams%26url=https://daddylive.live/embed/stream-36.php::LISTNAME:[B][COLORorangered]Link DaddyLive[/COLOR][/B]::#
	sublink:LISTSOURCE:plugin://plugin.video.SportsDevil/?mode=1&amp;item=catcher%3dstreams%26url=::LISTNAME:[B][COLORorangered]Link OFFLINE[/COLOR][/B]::#
	</link>
	<thumbnail>http://sportstvon.com/wp-content/uploads/2017/12/sky-arena.png</thumbnail>
	<fanart>-</fanart>
	<summary>I DO NOT OWN OR HOST THESE STREAMING LINKS.THEY ARE FREELY AVAILABLE ON THE INTERNET.Credits to the owners</summary>
</item>

item>
	<title>Sky Sports Cricket</title>
	<link>
	sublink:LISTSOURCE:plugin://plugin.video.SportsDevil/?mode=1&amp;item=catcher%3dstreams%26url=::LISTNAME:[B][COLORorangered]Link 1 OFFLINE[/COLOR][/B]::#
	sublink:LISTSOURCE:plugin://plugin.video.SportsDevil/?mode=1&amp;item=catcher%3dstreams%26url=::LISTNAME:[B][COLORorangered]Link 2 OFFLINE[/COLOR][/B]::#
	sublink:LISTSOURCE:plugin://plugin.video.SportsDevil/?mode=1&amp;item=catcher%3dstreams%26url=::LISTNAME:[B][COLORorangered]Link 3 OFFLINE[/COLOR][/B]::#
	</link>
	<thumbnail>https://i.imgur.com/KO1s0lE.png</thumbnail>
	<fanart>-</fanart>
	<summary>I DO NOT OWN OR HOST THESE STREAMING LINKS.THEY ARE FREELY AVAILABLE ON THE INTERNET.Credits to the owners</summary>
</item>

item>
	<title>Sky Sports F1</title>
	<link>
	sublink:LISTSOURCE:plugin://plugin.video.SportsDevil/?mode=1&amp;item=catcher%3dstreams%26url=::LISTNAME:[B][COLORgrey]Link 1[/COLOR][/B]::#
	sublink:LISTSOURCE:plugin://plugin.video.SportsDevil/?mode=1&amp;item=catcher%3dstreams%26url=::LISTNAME:[B][COLORgrey]Link 2[/COLOR][/B]::#
	</link>
	<thumbnail>http://i.imgur.com/BUuKpRw.png</thumbnail>
	<fanart>https://i.ytimg.com/vi/dPUiNofiCsI/maxresdefault.jpg</fanart>
	<summary>I DO NOT OWN OR HOST THESE STREAMING LINKS.THEY ARE FREELY AVAILABLE ON THE INTERNET.Credits to the owners</summary>
</item>

<item>
	<title>Sky Sports Football</title>
	<link>
	sublink:LISTSOURCE:plugin://plugin.video.SportsDevil/?mode=1&amp;item=catcher%3dstreams%26url=https://daddylive.live/embed/stream-35.php::LISTNAME:[B][COLORorangered]Link 1[/COLOR][/B]::#
	sublink:LISTSOURCE:plugin://plugin.video.SportsDevil/?mode=1&amp;item=catcher%3dstreams%26url=::LISTNAME:[B][COLORorangered]Link 2 OffLine[/COLOR][/B]::#
	</link>
	<thumbnail>https://i.imgur.com/qnoLouH.png</thumbnail>
	<fanart>-</fanart>
	<summary>I DO NOT OWN OR HOST THESE STREAMING LINKS.THEY ARE FREELY AVAILABLE ON THE INTERNET.Credits to the owners</summary>
</item>

item>
	<title>Sky Sports Golf</title>
	<link>	
	sublink:LISTSOURCE:plugin://plugin.video.SportsDevil/?mode=1&amp;item=catcher%3dstreams%26url=::LISTNAME:[B][COLORorangered]Link 1 SportsDevil[/COLOR][/B]::#
	sublink:LISTSOURCE:plugin://plugin.video.SportsDevil/?mode=1&amp;item=catcher%3dstreams%26url=::LISTNAME:[B][COLORorangered]Link 2 SportsDevil[/COLOR][/B]::#
	sublink:LISTSOURCE:plugin://plugin.video.SportsDevil/?mode=1&amp;item=catcher%3dstreams%26url=::LISTNAME:[B][COLORorangered]Link 3 SportsDevil[/COLOR][/B]::#
	</link>
	<thumbnail>https://i.imgur.com/UCBE1OI.png</thumbnail>
	<fanart>-</fanart>
	<summary>I DO NOT OWN OR HOST THESE STREAMING LINKS.THEY ARE FREELY AVAILABLE ON THE INTERNET.Credits to the owners</summary>
</item>

<item>
	<title>Sky Sports Main Event</title>
	<link>
	sublink:LISTSOURCE:plugin://plugin.video.SportsDevil/?mode=1&amp;item=catcher%3dstreams%26url=https://daddylive.live/embed/stream-38.php::LISTNAME:[B][COLORorangered]Link 1 DaddyLive[/COLOR][/B]::#
	sublink:LISTSOURCE:plugin://plugin.video.SportsDevil/?mode=1&amp;item=catcher%3dstreams%26url=http://tv4embed.com/ss1/ss1-stream1.php::LISTNAME:[B][COLORorangered]Link 2 Down[/COLOR][/B]::#
	</link>
	<thumbnail>https://i.imgur.com/aR33kqd.png</thumbnail>
	<fanart>-</fanart>
	<summary>I DO NOT OWN OR HOST THESE STREAMING LINKS.THEY ARE FREELY AVAILABLE ON THE INTERNET.Credits to the owners</summary>
</item>

item>
	<title>Sky Sports Motor GP</title>
	<link>
	sublink:LISTSOURCE:plugin://plugin.video.SportsDevil/?mode=1&amp;item=catcher%3dstreams%26url=::LISTNAME:[B][COLORorangered]Link 1| [/COLOR][/B]::#
	sublink:LISTSOURCE:plugin://plugin.video.SportsDevil/?mode=1&amp;item=catcher%3dstreams%26url=::LISTNAME:[B][COLORorangered]Link 2| [/COLOR][/B]::#
	</link>
	<thumbnail>https://pbs.twimg.com/profile_images/1013547267666644993/khbZuaoh_400x400.jpg</thumbnail>
	<fanart>-</fanart>
	<summary>I DO NOT OWN OR HOST THESE STREAMING LINKS.THEY ARE FREELY AVAILABLE ON THE INTERNET.Credits to the owners</summary>
</item>

item>
	<title>Sky Sports Mix</title>
	<link>
	sublink:LISTSOURCE:plugin://plugin.video.SportsDevil/?mode=1&amp;item=catcher%3dstreams%26url=::LISTNAME:[B][COLORorangered]Link 1| [/COLOR][/B]::#
	sublink:LISTSOURCE:plugin://plugin.video.SportsDevil/?mode=1&amp;item=catcher%3dstreams%26url=::LISTNAME:[B][COLORorangered]Link 2| [/COLOR][/B]::#
	</link>
	<thumbnail>http://tvprofil.net/img/kanali-logo/Sky_Sports_Mix_logo.png</thumbnail>
	<fanart>http://e0.365dm.com/16/08/16-9/20/sky-sports-presenters_3759513.jpg?20160807075529</fanart>
	<summary>I DO NOT OWN OR HOST THESE STREAMING LINKS.THEY ARE FREELY AVAILABLE ON THE INTERNET.Credits to the owners</summary>
</item>

item>
	<title>Sky Sports News</title>
	<link>
	sublink:LISTSOURCE:plugin://plugin.video.SportsDevil/?mode=1&amp;item=catcher%3dstreams%26url=::LISTNAME:[B][COLORorangered]Link 1[/COLOR][/B]::#
	sublink:LISTSOURCE:plugin://plugin.video.SportsDevil/?mode=1&amp;item=catcher%3dstreams%26url=::LISTNAME:[B][COLORorangered]Link 2 OFFLINE[/COLOR][/B]::#
	</link>
	<thumbnail>https://img.schnaeppchenfuchs.com/img/a1/f4/20/skyp.jpg?arw=1&h=240&lossless=1&q=70&auto=compress%2Cformat</thumbnail>
	<fanart>http://e0.365dm.com/16/08/16-9/20/sky-sports-presenters_3759513.jpg?20160807075529</fanart>
	<summary>I DO NOT OWN OR HOST THESE STREAMING LINKS.THEY ARE FREELY AVAILABLE ON THE INTERNET.Credits to the owners</summary>
</item>

<item>
	<title>Sky Sports Premier League</title>
	<link>
	sublink:LISTSOURCE:plugin://plugin.video.SportsDevil/?mode=1&amp;item=catcher%3dstreams%26url=https://daddylive.live/embed/stream-46.php::LISTNAME:[B][COLORorangered]Link 1 daddyLive[/COLOR][/B]::#
	sublink:LISTSOURCE:plugin://plugin.video.SportsDevil/?mode=1&amp;item=catcher%3dstreams%26url=::LISTNAME:[B][COLORorangered]Link 2 OFFLINE[/COLOR][/B]::#
	</link>
	<thumbnail>https://i.imgur.com/CGNeotr.png</thumbnail>
	<fanart>-</fanart>
	<summary>I DO NOT OWN OR HOST THESE STREAMING LINKS.THEY ARE FREELY AVAILABLE ON THE INTERNET.Credits to the owners</summary>
</item>

item>
	<title>SportsNet 360</title>
	<link>
	sublink:LISTSOURCE:plugin://plugin.video.SportsDevil/?mode=1&amp;item=catcher%3dstreams%26url=::LISTNAME:[B][COLORorangered]Link 1| [/COLOR][/B]::#
	sublink:LISTSOURCE:plugin://plugin.video.SportsDevil/?mode=1&amp;item=catcher%3dstreams%26url=::LISTNAME:[B][COLORorangered]Link 2| [/COLOR][/B]::#
	</link>
	<thumbnail>https://i.imgur.com/1ZyGDc7.jpg</thumbnail>
	<fanart>http://assets3.sportsnet.ca/wp-content/uploads/2013/06/sportsnet360.png</fanart>
	<summary>I DO NOT OWN OR HOST THESE STREAMING LINKS.THEY ARE FREELY AVAILABLE ON THE INTERNET.Credits to the owners</summary>
</item>

item>
	<title>Sportsnet East</title>
	<link>
	sublink:LISTSOURCE:plugin://plugin.video.SportsDevil/?mode=1&amp;item=catcher%3dstreams%26url=::LISTNAME:[B][COLORorangered]Link 1| [/COLOR][/B]::#
	sublink:LISTSOURCE:plugin://plugin.video.SportsDevil/?mode=1&amp;item=catcher%3dstreams%26url=::LISTNAME:[B][COLORorangered]Link 2| [/COLOR][/B]::#
	</link>
	<thumbnail>https://i.imgur.com/1ZyGDc7.jpg</thumbnail>
	<fanart>http://assets3.sportsnet.ca/wp-content/uploads/2013/06/sportsnet360.png</fanart>
	<summary>I DO NOT OWN OR HOST THESE STREAMING LINKS.THEY ARE FREELY AVAILABLE ON THE INTERNET.Credits to the owners</summary>
</item>

item>
	<title>SportsNet One</title>
	<link>
	sublink:LISTSOURCE:plugin://plugin.video.SportsDevil/?mode=1&amp;item=catcher%3dstreams%26url=::LISTNAME:[B][COLORorangered]Link 1| [/COLOR][/B]::#
	sublink:LISTSOURCE:plugin://plugin.video.SportsDevil/?mode=1&amp;item=catcher%3dstreams%26url=::LISTNAME:[B][COLORorangered]Link 2| [/COLOR][/B]::#
	</link>
	<thumbnail>https://i.imgur.com/1ZyGDc7.jpg</thumbnail>
	<fanart>http://assets3.sportsnet.ca/wp-content/uploads/2013/06/sportsnet360.png</fanart>
	<summary>I DO NOT OWN OR HOST THESE STREAMING LINKS.THEY ARE FREELY AVAILABLE ON THE INTERNET.Credits to the owners</summary>
</item>


item>
	<title>SportsNet Ontario</title>
	<link>
	sublink:LISTSOURCE:plugin://plugin.video.SportsDevil/?mode=1&amp;item=catcher%3dstreams%26url=::LISTNAME:[B][COLORorangered]Link 1| [/COLOR][/B]::#
	sublink:LISTSOURCE:plugin://plugin.video.SportsDevil/?mode=1&amp;item=catcher%3dstreams%26url=::LISTNAME:[B][COLORorangered]Link 2| [/COLOR][/B]::#
	</link>
	<thumbnail>https://i.imgur.com/1ZyGDc7.jpg</thumbnail>
	<fanart>http://assets3.sportsnet.ca/wp-content/uploads/2013/06/sportsnet360.png</fanart>
	<summary>I DO NOT OWN OR HOST THESE STREAMING LINKS.THEY ARE FREELY AVAILABLE ON THE INTERNET.Credits to the owners</summary>
</item>

item>
	<title>Sportsnet Pacific</title>
	<link>
	sublink:LISTSOURCE:plugin://plugin.video.SportsDevil/?mode=1&amp;item=catcher%3dstreams%26url=::LISTNAME:[B][COLORorangered]Link 1| [/COLOR][/B]::#
	sublink:LISTSOURCE:plugin://plugin.video.SportsDevil/?mode=1&amp;item=catcher%3dstreams%26url=::LISTNAME:[B][COLORorangered]Link 2| [/COLOR][/B]::#
	</link>
	<thumbnail>https://i.imgur.com/1ZyGDc7.jpg</thumbnail>
	<fanart>http://assets3.sportsnet.ca/wp-content/uploads/2013/06/sportsnet360.png</fanart>
	<summary>I DO NOT OWN OR HOST THESE STREAMING LINKS.THEY ARE FREELY AVAILABLE ON THE INTERNET.Credits to the owners</summary>
</item>

item>
	<title>SportsNet West</title>
	<link>
	sublink:LISTSOURCE:plugin://plugin.video.SportsDevil/?mode=1&amp;item=catcher%3dstreams%26url=::LISTNAME:[B][COLORorangered]Link 1| [/COLOR][/B]::#
	sublink:LISTSOURCE:plugin://plugin.video.SportsDevil/?mode=1&amp;item=catcher%3dstreams%26url=::LISTNAME:[B][COLORorangered]Link 2| [/COLOR][/B]::#
	</link>
	<thumbnail>https://i.imgur.com/1ZyGDc7.jpg</thumbnail>
	<fanart>http://assets3.sportsnet.ca/wp-content/uploads/2013/06/sportsnet360.png</fanart>
	<summary>I DO NOT OWN OR HOST THESE STREAMING LINKS.THEY ARE FREELY AVAILABLE ON THE INTERNET.Credits to the owners</summary>
</item>

item>
	<title>SportsNet World</title>
	<link>
	sublink:LISTSOURCE:plugin://plugin.video.SportsDevil/?mode=1&amp;item=catcher%3dstreams%26url=::LISTNAME:[B][COLORorangered]Link 1| [/COLOR][/B]::#
	sublink:LISTSOURCE:plugin://plugin.video.SportsDevil/?mode=1&amp;item=catcher%3dstreams%26url=::LISTNAME:[B][COLORorangered]Link 2| [/COLOR][/B]::#
	</link>
	<thumbnail>https://i.imgur.com/1ZyGDc7.jpg</thumbnail>
	<fanart>http://assets3.sportsnet.ca/wp-content/uploads/2013/06/sportsnet360.png</fanart>
	<summary>I DO NOT OWN OR HOST THESE STREAMING LINKS.THEY ARE FREELY AVAILABLE ON THE INTERNET.Credits to the owners</summary>
</item>



item>
	<title>TSN1</title>
	<link>
	sublink:LISTSOURCE:plugin://plugin.video.SportsDevil/?mode=1&amp;item=catcher%3dstreams%26url=::LISTNAME:[B][COLORorangered]Link 1| [/COLOR][/B]::#
	sublink:LISTSOURCE:plugin://plugin.video.SportsDevil/?mode=1&amp;item=catcher%3dstreams%26url=::LISTNAME:[B][COLORorangered]Link 2| [/COLOR][/B]::#
	<thumbnail>https://imgur.com/PAf9gRf.jpg</thumbnail>
	<fanart>https://www.tsn.ca/polopoly_fs/1.354057!/fileimage/httpImage/image.png_gen/derivatives/landscape_620/tsn.png</fanart>
	<summary>I DO NOT OWN OR HOST THESE STREAMING LINKS.THEY ARE FREELY AVAILABLE ON THE INTERNET.Credits to the owners</summary>
</item>

item>
	<title>TSN2</title>
	<link>
	sublink:LISTSOURCE:plugin://plugin.video.SportsDevil/?mode=1&amp;item=catcher%3dstreams%26url=::LISTNAME:[B][COLORorangered]Link 1| [/COLOR][/B]::#
	sublink:LISTSOURCE:plugin://plugin.video.SportsDevil/?mode=1&amp;item=catcher%3dstreams%26url=::LISTNAME:[B][COLORorangered]Link 2| [/COLOR][/B]::#
	</link>
	<thumbnail>https://imgur.com/vUl1I2U.jpg</thumbnail>
	<fanart>https://www.tsn.ca/polopoly_fs/1.354057!/fileimage/httpImage/image.png_gen/derivatives/landscape_620/tsn.png</fanart>
	<summary>I DO NOT OWN OR HOST THESE STREAMING LINKS.THEY ARE FREELY AVAILABLE ON THE INTERNET.Credits to the owners</summary>
</item>

item>
	<title>TSN3</title>
	<link>
	sublink:LISTSOURCE:plugin://plugin.video.SportsDevil/?mode=1&amp;item=catcher%3dstreams%26url=::LISTNAME:[B][COLORorangered]Link 1| [/COLOR][/B]::#
	sublink:LISTSOURCE:plugin://plugin.video.SportsDevil/?mode=1&amp;item=catcher%3dstreams%26url=::LISTNAME:[B][COLORorangered]Link 2| [/COLOR][/B]::#
	</link>
	<thumbnail>https://imgur.com/ncWIimS.jpg</thumbnail>
	<fanart>https://www.tsn.ca/polopoly_fs/1.354057!/fileimage/httpImage/image.png_gen/derivatives/landscape_620/tsn.png</fanart>
	<summary>I DO NOT OWN OR HOST THESE STREAMING LINKS.THEY ARE FREELY AVAILABLE ON THE INTERNET.Credits to the owners</summary>
</item>

item>
	<title>TSN4</title>
	<link>
	sublink:LISTSOURCE:plugin://plugin.video.SportsDevil/?mode=1&amp;item=catcher%3dstreams%26url=::LISTNAME:[B][COLORorangered]Link 1| [/COLOR][/B]::#
	sublink:LISTSOURCE:plugin://plugin.video.SportsDevil/?mode=1&amp;item=catcher%3dstreams%26url=::LISTNAME:[B][COLORorangered]Link 2| [/COLOR][/B]::#
	</link>
	<thumbnail>https://imgur.com/8BWgSpz.jpg</thumbnail>
	<fanart>https://www.tsn.ca/polopoly_fs/1.354057!/fileimage/httpImage/image.png_gen/derivatives/landscape_620/tsn.png</fanart>
	<summary>I DO NOT OWN OR HOST THESE STREAMING LINKS.THEY ARE FREELY AVAILABLE ON THE INTERNET.Credits to the owners</summary>
</item>

item>
	<title>TSN5</title>
	<link>
	sublink:LISTSOURCE:plugin://plugin.video.SportsDevil/?mode=1&amp;item=catcher%3dstreams%26url=::LISTNAME:[B][COLORorangered]Link 1| [/COLOR][/B]::#
	sublink:LISTSOURCE:plugin://plugin.video.SportsDevil/?mode=1&amp;item=catcher%3dstreams%26url=::LISTNAME:[B][COLORorangered]Link 2| [/COLOR][/B]::#
	</link>
	<thumbnail>http://www.nowgoal.tv/wp-content/uploads/2017/11/tsn5-565x318.png</thumbnail>
	<fanart>https://www.tsn.ca/polopoly_fs/1.354057!/fileimage/httpImage/image.png_gen/derivatives/landscape_620/tsn.png</fanart>
	<summary>I DO NOT OWN OR HOST THESE STREAMING LINKS.THEY ARE FREELY AVAILABLE ON THE INTERNET.Credits to the owners</summary>
</item>


<item>
	<title>WWE Network</title>
	<link>
	sublink:LISTSOURCE:plugin://plugin.video.SportsDevil/?mode=1&amp;item=catcher%3dstreams%26url=::LISTNAME:[B][COLORorangered]Link 1| [/COLOR][/B]::#
	sublink:LISTSOURCE:plugin://plugin.video.SportsDevil/?mode=1&amp;item=catcher%3dstreams%26url=::LISTNAME:[B][COLORorangered]Link 2| [/COLOR][/B]::#
	</link>
	<thumbnail>https://archive.org/download/tvlogos/WWE%20Network.png</thumbnail>
	<fanart>-</fanart>
	<summary>I DO NOT OWN OR HOST THESE STREAMING LINKS.THEY ARE FREELY AVAILABLE ON THE INTERNET.Credits to the owners</summary>
</item>

<item>
	<title>WWE TV</title>
	<link>
	sublink:LISTSOURCE:plugin://plugin.video.SportsDevil/?mode=1&amp;item=catcher%3dstreams%26url=::LISTNAME:[B][COLORorangered]Link 1| [/COLOR][/B]::#
	sublink:LISTSOURCE:plugin://plugin.video.SportsDevil/?mode=1&amp;item=catcher%3dstreams%26url=::LISTNAME:[B][COLORorangered]Link 2| [/COLOR][/B]::#
	</link>
	<thumbnail>https://i.imgur.com/qnz28T5.png</thumbnail>
	<fanart>-</fanart>
	<summary>I DO NOT OWN OR HOST THESE STREAMING LINKS.THEY ARE FREELY AVAILABLE ON THE INTERNET.Credits to the owners</summary>
</item>

=======================================================
https://vertelevision.tv
http://ott-cdn.ucom.am/s81/index.m3u8
http://ott-cdn.ucom.am/s82/index.m3u8